lazydog-0.1.1.dist-info/WHEEL
lazydog-0.1.1.dist-info/DESCRIPTION.rst
lazydog-0.1.1.dist-info/RECORD
lazydog-0.1.1.dist-info/top_level.txt
lazydog-0.1.1.dist-info/entry_points.txt
lazydog-0.1.1.dist-info/METADATA
lazydog-0.1.1.dist-info/metadata.json
lazydog/lazydog.py
lazydog/states.py
lazydog/__init__.py
lazydog/dropbox_content_hasher.py
lazydog/events.py
lazydog/handlers.py
lazydog/queues.py
lazydog/revised_watchdog/__init__.py
lazydog/revised_watchdog/events.py
lazydog/revised_watchdog/observers/__init__.py
lazydog/revised_watchdog/observers/inotify.py
lazydog/revised_watchdog/observers/inotify_buffer.py
lazydog/revised_watchdog/observers/inotify_c.py
